{
  "globals": {
    "useSummaryCreateFormStore": "readonly",
    "useAuthStore": "readonly",
    "useLayout": "readonly",
    "useNavigationMenu": "readonly",
    "useAPI": "readonly",
    "createDebounceFetch": "readonly",
    "fetchWithCookie": "readonly",
    "usePrimeDataTable": "readonly",
    "ExpiringStorage": "readonly",
    "QueryBuilder": "readonly",
    "updateTheme": "readonly",
    "useThemeStore": "readonly",
    "usePrimeVue": "readonly",
    "useStyle": "readonly",
    "useConfirm": "readonly",
    "useToast": "readonly",
    "useDialog": "readonly",
    "defineStore": "readonly",
    "acceptHMRUpdate": "readonly",
    "usePinia": "readonly",
    "storeToRefs": "readonly",
    "persistedState": "readonly",
    "useI18n": "readonly",
    "useRouteBaseName": "readonly",
    "useLocalePath": "readonly",
    "useLocaleRoute": "readonly",
    "useSwitchLocalePath": "readonly",
    "useLocaleHead": "readonly",
    "useBrowserLocale": "readonly",
    "useCookieLocale": "readonly",
    "useSetI18nParams": "readonly",
    "defineI18nRoute": "readonly",
    "defineI18nLocale": "readonly",
    "defineI18nConfig": "readonly",
    "queryContent": "readonly",
    "useContentHelpers": "readonly",
    "useContentHead": "readonly",
    "useContentPreview": "readonly",
    "withContentBase": "readonly",
    "useUnwrap": "readonly",
    "fetchContentNavigation": "readonly",
    "useContentState": "readonly",
    "useContent": "readonly",
    "unwrapSlot": "readonly",
    "parseMarkdown": "readonly"
  }
}
